{
 "families": [
  {
   "name": "gen_000",
   "trace": [
    0,
    1,
    2,
    1,
    0,
    1,
    0,
    1,
    0
   ],
   "node_roles": [
    "claim",
    "record",
    "metric"
   ],
   "edge_labels": [
    [
     "CONTRADICTS",
     "in"
    ],
    [
     "MEASURES",
     "out"
    ],
    [
     "MEASURES",
     "in"
    ],
    [
     "CONTRADICTS",
     "out"
    ],
    [
     "SUPPORTS",
     "in"
    ],
    [
     "WEAKENS",
     "out"
    ],
    [
     "CONTRADICTS",
     "in"
    ],
    [
     "WEAKENS",
     "out"
    ]
   ],
   "properties": [
    "recurrence",
    "branch",
    "convergence",
    "repeated_subtrace",
    "loop_closure"
   ],
   "typed_key": "n=3;t=0>1>2>1>0>1>0>1>0;el=\u2014,CONTRADICTS|in,MEASURES|out,MEASURES|in,CONTRADICTS|out,SUPPORTS|in,WEAKENS|out,CONTRADICTS|in,WEAKENS|out;e=0-CONTRADICTS|in->1,0-SUPPORTS|in->1,1-CONTRADICTS|out->0,1-MEASURES|out->2,1-WEAKENS|out->0,2-MEASURES|in->1;c=0-CONTRADICTS|in->1:2,0-SUPPORTS|in->1:1,1-CONTRADICTS|out->0:1,1-MEASURES|out->2:1,1-WEAKENS|out->0:2,2-MEASURES|in->1:1",
   "labelfree_key": "n=3;t=0>1>2>1>0>1>0>1>0;el=\u2014,\u2014,\u2014,\u2014,\u2014,\u2014,\u2014,\u2014,\u2014;e=0-\u2014->1,1-\u2014->0,1-\u2014->2,2-\u2014->1;c=0-\u2014->1:3,1-\u2014->0:3,1-\u2014->2:1,2-\u2014->1:1",
   "instances": [
    {
     "labels": [
      "K-gen_000-00-00",
      "L-gen_000-00-01",
      "Q-gen_000-00-02",
      "L-gen_000-00-01",
      "K-gen_000-00-00",
      "L-gen_000-00-01",
      "K-gen_000-00-00",
      "L-gen_000-00-01",
      "K-gen_000-00-00"
     ],
     "walk": [
      [
       "K-gen_000-00-00",
       null,
       null
      ],
      [
       "L-gen_000-00-01",
       "CONTRADICTS",
       "in"
      ],
      [
       "Q-gen_000-00-02",
       "MEASURES",
       "out"
      ],
      [
       "L-gen_000-00-01",
       "MEASURES",
       "in"
      ],
      [
       "K-gen_000-00-00",
       "CONTRADICTS",
       "out"
      ],
      [
       "L-gen_000-00-01",
       "SUPPORTS",
       "in"
      ],
      [
       "K-gen_000-00-00",
       "WEAKENS",
       "out"
      ],
      [
       "L-gen_000-00-01",
       "CONTRADICTS",
       "in"
      ],
      [
       "K-gen_000-00-00",
       "WEAKENS",
       "out"
      ]
     ]
    },
    {
     "labels": [
      "K-gen_000-01-00",
      "L-gen_000-01-01",
      "Q-gen_000-01-02",
      "L-gen_000-01-01",
      "K-gen_000-01-00",
      "L-gen_000-01-01",
      "K-gen_000-01-00",
      "L-gen_000-01-01",
      "K-gen_000-01-00"
     ],
     "walk": [
      [
       "K-gen_000-01-00",
       null,
       null
      ],
      [
       "L-gen_000-01-01",
       "CONTRADICTS",
       "in"
      ],
      [
       "Q-gen_000-01-02",
       "MEASURES",
       "out"
      ],
      [
       "L-gen_000-01-01",
       "MEASURES",
       "in"
      ],
      [
       "K-gen_000-01-00",
       "CONTRADICTS",
       "out"
      ],
      [
       "L-gen_000-01-01",
       "SUPPORTS",
       "in"
      ],
      [
       "K-gen_000-01-00",
       "WEAKENS",
       "out"
      ],
      [
       "L-gen_000-01-01",
       "CONTRADICTS",
       "in"
      ],
      [
       "K-gen_000-01-00",
       "WEAKENS",
       "out"
      ]
     ]
    },
    {
     "labels": [
      "K-gen_000-02-00",
      "L-gen_000-02-01",
      "Q-gen_000-02-02",
      "L-gen_000-02-01",
      "K-gen_000-02-00",
      "L-gen_000-02-01",
      "K-gen_000-02-00",
      "L-gen_000-02-01",
      "K-gen_000-02-00"
     ],
     "walk": [
      [
       "K-gen_000-02-00",
       null,
       null
      ],
      [
       "L-gen_000-02-01",
       "CONTRADICTS",
       "in"
      ],
      [
       "Q-gen_000-02-02",
       "MEASURES",
       "out"
      ],
      [
       "L-gen_000-02-01",
       "MEASURES",
       "in"
      ],
      [
       "K-gen_000-02-00",
       "CONTRADICTS",
       "out"
      ],
      [
       "L-gen_000-02-01",
       "SUPPORTS",
       "in"
      ],
      [
       "K-gen_000-02-00",
       "WEAKENS",
       "out"
      ],
      [
       "L-gen_000-02-01",
       "CONTRADICTS",
       "in"
      ],
      [
       "K-gen_000-02-00",
       "WEAKENS",
       "out"
      ]
     ]
    }
   ]
  },
  {
   "name": "gen_001",
   "trace": [
    0,
    0,
    0,
    1,
    2,
    3,
    4,
    3,
    0
   ],
   "node_roles": [
    "claim",
    "record",
    "metric",
    "record",
    "domain"
   ],
   "edge_labels": [
    [
     "SUPERSEDED_BY",
     "in"
    ],
    [
     "SUPERSEDED_BY",
     "out"
    ],
    [
     "SUPPORTS",
     "in"
    ],
    [
     "MEASURES",
     "out"
    ],
    [
     "MEASURES",
     "in"
    ],
    [
     "IN_DOMAIN",
     "out"
    ],
    [
     "IN_DOMAIN",
     "in"
    ],
    [
     "SUPPORTS",
     "out"
    ]
   ],
   "properties": [
    "recurrence",
    "branch",
    "convergence",
    "loop_closure"
   ],
   "typed_key": "n=5;t=0>0>0>1>2>3>4>3>0;el=\u2014,SUPERSEDED_BY|in,SUPERSEDED_BY|out,SUPPORTS|in,MEASURES|out,MEASURES|in,IN_DOMAIN|out,IN_DOMAIN|in,SUPPORTS|out;e=0-SUPERSEDED_BY|in->0,0-SUPERSEDED_BY|out->0,0-SUPPORTS|in->1,1-MEASURES|out->2,2-MEASURES|in->3,3-IN_DOMAIN|out->4,3-SUPPORTS|out->0,4-IN_DOMAIN|in->3;c=0-SUPERSEDED_BY|in->0:1,0-SUPERSEDED_BY|out->0:1,0-SUPPORTS|in->1:1,1-MEASURES|out->2:1,2-MEASURES|in->3:1,3-IN_DOMAIN|out->4:1,3-SUPPORTS|out->0:1,4-IN_DOMAIN|in->3:1",
   "labelfree_key": "n=5;t=0>0>0>1>2>3>4>3>0;el=\u2014,\u2014,\u2014,\u2014,\u2014,\u2014,\u2014,\u2014,\u2014;e=0-\u2014->0,0-\u2014->1,1-\u2014->2,2-\u2014->3,3-\u2014->0,3-\u2014->4,4-\u2014->3;c=0-\u2014->0:2,0-\u2014->1:1,1-\u2014->2:1,2-\u2014->3:1,3-\u2014->0:1,3-\u2014->4:1,4-\u2014->3:1",
   "instances": [
    {
     "labels": [
      "K-gen_001-00-00",
      "K-gen_001-00-00",
      "K-gen_001-00-00",
      "L-gen_001-00-01",
      "Q-gen_001-00-02",
      "L-gen_001-00-03",
      "D-gen_001-00-04",
      "L-gen_001-00-03",
      "K-gen_001-00-00"
     ],
     "walk": [
      [
       "K-gen_001-00-00",
       null,
       null
      ],
      [
       "K-gen_001-00-00",
       "SUPERSEDED_BY",
       "in"
      ],
      [
       "K-gen_001-00-00",
       "SUPERSEDED_BY",
       "out"
      ],
      [
       "L-gen_001-00-01",
       "SUPPORTS",
       "in"
      ],
      [
       "Q-gen_001-00-02",
       "MEASURES",
       "out"
      ],
      [
       "L-gen_001-00-03",
       "MEASURES",
       "in"
      ],
      [
       "D-gen_001-00-04",
       "IN_DOMAIN",
       "out"
      ],
      [
       "L-gen_001-00-03",
       "IN_DOMAIN",
       "in"
      ],
      [
       "K-gen_001-00-00",
       "SUPPORTS",
       "out"
      ]
     ]
    },
    {
     "labels": [
      "K-gen_001-01-00",
      "K-gen_001-01-00",
      "K-gen_001-01-00",
      "L-gen_001-01-01",
      "Q-gen_001-01-02",
      "L-gen_001-01-03",
      "D-gen_001-01-04",
      "L-gen_001-01-03",
      "K-gen_001-01-00"
     ],
     "walk": [
      [
       "K-gen_001-01-00",
       null,
       null
      ],
      [
       "K-gen_001-01-00",
       "SUPERSEDED_BY",
       "in"
      ],
      [
       "K-gen_001-01-00",
       "SUPERSEDED_BY",
       "out"
      ],
      [
       "L-gen_001-01-01",
       "SUPPORTS",
       "in"
      ],
      [
       "Q-gen_001-01-02",
       "MEASURES",
       "out"
      ],
      [
       "L-gen_001-01-03",
       "MEASURES",
       "in"
      ],
      [
       "D-gen_001-01-04",
       "IN_DOMAIN",
       "out"
      ],
      [
       "L-gen_001-01-03",
       "IN_DOMAIN",
       "in"
      ],
      [
       "K-gen_001-01-00",
       "SUPPORTS",
       "out"
      ]
     ]
    },
    {
     "labels": [
      "K-gen_001-02-00",
      "K-gen_001-02-00",
      "K-gen_001-02-00",
      "L-gen_001-02-01",
      "Q-gen_001-02-02",
      "L-gen_001-02-03",
      "D-gen_001-02-04",
      "L-gen_001-02-03",
      "K-gen_001-02-00"
     ],
     "walk": [
      [
       "K-gen_001-02-00",
       null,
       null
      ],
      [
       "K-gen_001-02-00",
       "SUPERSEDED_BY",
       "in"
      ],
      [
       "K-gen_001-02-00",
       "SUPERSEDED_BY",
       "out"
      ],
      [
       "L-gen_001-02-01",
       "SUPPORTS",
       "in"
      ],
      [
       "Q-gen_001-02-02",
       "MEASURES",
       "out"
      ],
      [
       "L-gen_001-02-03",
       "MEASURES",
       "in"
      ],
      [
       "D-gen_001-02-04",
       "IN_DOMAIN",
       "out"
      ],
      [
       "L-gen_001-02-03",
       "IN_DOMAIN",
       "in"
      ],
      [
       "K-gen_001-02-00",
       "SUPPORTS",
       "out"
      ]
     ]
    }
   ]
  },
  {
   "name": "gen_002",
   "trace": [
    0,
    1,
    2,
    3,
    4,
    1,
    4,
    3,
    4
   ],
   "node_roles": [
    "claim",
    "record",
    "method",
    "record",
    "metric"
   ],
   "edge_labels": [
    [
     "SUPPORTS",
     "in"
    ],
    [
     "USES_METHOD",
     "out"
    ],
    [
     "USES_METHOD",
     "in"
    ],
    [
     "MEASURES",
     "out"
    ],
    [
     "MEASURES",
     "in"
    ],
    [
     "MEASURES",
     "out"
    ],
    [
     "MEASURES",
     "in"
    ],
    [
     "MEASURES",
     "out"
    ]
   ],
   "properties": [
    "recurrence",
    "branch",
    "convergence",
    "repeated_subtrace"
   ],
   "typed_key": "n=5;t=0>1>2>3>4>1>4>3>4;el=\u2014,SUPPORTS|in,USES_METHOD|out,USES_METHOD|in,MEASURES|out,MEASURES|in,MEASURES|out,MEASURES|in,MEASURES|out;e=0-SUPPORTS|in->1,1-MEASURES|out->4,1-USES_METHOD|out->2,2-USES_METHOD|in->3,3-MEASURES|out->4,4-MEASURES|in->1,4-MEASURES|in->3;c=0-SUPPORTS|in->1:1,1-MEASURES|out->4:1,1-USES_METHOD|out->2:1,2-USES_METHOD|in->3:1,3-MEASURES|out->4:2,4-MEASURES|in->1:1,4-MEASURES|in->3:1",
   "labelfree_key": "n=5;t=0>1>2>3>4>1>4>3>4;el=\u2014,\u2014,\u2014,\u2014,\u2014,\u2014,\u2014,\u2014,\u2014;e=0-\u2014->1,1-\u2014->2,1-\u2014->4,2-\u2014->3,3-\u2014->4,4-\u2014->1,4-\u2014->3;c=0-\u2014->1:1,1-\u2014->2:1,1-\u2014->4:1,2-\u2014->3:1,3-\u2014->4:2,4-\u2014->1:1,4-\u2014->3:1",
   "instances": [
    {
     "labels": [
      "K-gen_002-00-00",
      "L-gen_002-00-01",
      "M-gen_002-00-02",
      "L-gen_002-00-03",
      "Q-gen_002-00-04",
      "L-gen_002-00-01",
      "Q-gen_002-00-04",
      "L-gen_002-00-03",
      "Q-gen_002-00-04"
     ],
     "walk": [
      [
       "K-gen_002-00-00",
       null,
       null
      ],
      [
       "L-gen_002-00-01",
       "SUPPORTS",
       "in"
      ],
      [
       "M-gen_002-00-02",
       "USES_METHOD",
       "out"
      ],
      [
       "L-gen_002-00-03",
       "USES_METHOD",
       "in"
      ],
      [
       "Q-gen_002-00-04",
       "MEASURES",
       "out"
      ],
      [
       "L-gen_002-00-01",
       "MEASURES",
       "in"
      ],
      [
       "Q-gen_002-00-04",
       "MEASURES",
       "out"
      ],
      [
       "L-gen_002-00-03",
       "MEASURES",
       "in"
      ],
      [
       "Q-gen_002-00-04",
       "MEASURES",
       "out"
      ]
     ]
    },
    {
     "labels": [
      "K-gen_002-01-00",
      "L-gen_002-01-01",
      "M-gen_002-01-02",
      "L-gen_002-01-03",
      "Q-gen_002-01-04",
      "L-gen_002-01-01",
      "Q-gen_002-01-04",
      "L-gen_002-01-03",
      "Q-gen_002-01-04"
     ],
     "walk": [
      [
       "K-gen_002-01-00",
       null,
       null
      ],
      [
       "L-gen_002-01-01",
       "SUPPORTS",
       "in"
      ],
      [
       "M-gen_002-01-02",
       "USES_METHOD",
       "out"
      ],
      [
       "L-gen_002-01-03",
       "USES_METHOD",
       "in"
      ],
      [
       "Q-gen_002-01-04",
       "MEASURES",
       "out"
      ],
      [
       "L-gen_002-01-01",
       "MEASURES",
       "in"
      ],
      [
       "Q-gen_002-01-04",
       "MEASURES",
       "out"
      ],
      [
       "L-gen_002-01-03",
       "MEASURES",
       "in"
      ],
      [
       "Q-gen_002-01-04",
       "MEASURES",
       "out"
      ]
     ]
    },
    {
     "labels": [
      "K-gen_002-02-00",
      "L-gen_002-02-01",
      "M-gen_002-02-02",
      "L-gen_002-02-03",
      "Q-gen_002-02-04",
      "L-gen_002-02-01",
      "Q-gen_002-02-04",
      "L-gen_002-02-03",
      "Q-gen_002-02-04"
     ],
     "walk": [
      [
       "K-gen_002-02-00",
       null,
       null
      ],
      [
       "L-gen_002-02-01",
       "SUPPORTS",
       "in"
      ],
      [
       "M-gen_002-02-02",
       "USES_METHOD",
       "out"
      ],
      [
       "L-gen_002-02-03",
       "USES_METHOD",
       "in"
      ],
      [
       "Q-gen_002-02-04",
       "MEASURES",
       "out"
      ],
      [
       "L-gen_002-02-01",
       "MEASURES",
       "in"
      ],
      [
       "Q-gen_002-02-04",
       "MEASURES",
       "out"
      ],
      [
       "L-gen_002-02-03",
       "MEASURES",
       "in"
      ],
      [
       "Q-gen_002-02-04",
       "MEASURES",
       "out"
      ]
     ]
    }
   ]
  }
 ],
 "polysemy": [
  {
   "pair_id": 0,
   "family_a": "poly_A_000",
   "family_b": "poly_B_000",
   "share_k": 4,
   "walk_a": [
    [
     "K-poly_A_000-00-00",
     null,
     null
    ],
    [
     "K-poly_A_000-00-00",
     "SUPERSEDED_BY",
     "in"
    ],
    [
     "L-poly_A_000-00-01",
     "WEAKENS",
     "in"
    ],
    [
     "K-poly_A_000-00-02",
     "CONTRADICTS",
     "out"
    ],
    [
     "L-poly_A_000-00-01",
     "WEAKENS",
     "in"
    ],
    [
     "V-poly_A_000-00-03",
     "HAS_VERDICT",
     "out"
    ],
    [
     "L-poly_A_000-00-04",
     "HAS_VERDICT",
     "in"
    ],
    [
     "K-poly_A_000-00-00",
     "SUPPORTS",
     "out"
    ],
    [
     "L-poly_A_000-00-04",
     "WEAKENS",
     "in"
    ]
   ],
   "walk_b": [
    [
     "K-poly_B_000-00-00",
     null,
     null
    ],
    [
     "K-poly_B_000-00-00",
     "SUPERSEDED_BY",
     "in"
    ],
    [
     "L-poly_B_000-00-01",
     "WEAKENS",
     "in"
    ],
    [
     "K-poly_B_000-00-02",
     "CONTRADICTS",
     "out"
    ],
    [
     "L-poly_B_000-00-03",
     "CONTRADICTS",
     "in"
    ]
   ],
   "sig_a": "n=5;t=0>0>1>2>1>3>4>0>4;el=\u2014,SUPERSEDED_BY|in,WEAKENS|in,CONTRADICTS|out,WEAKENS|in,HAS_VERDICT|out,HAS_VERDICT|in,SUPPORTS|out,WEAKENS|in;e=0-SUPERSEDED_BY|in->0,0-WEAKENS|in->1,0-WEAKENS|in->4,1-CONTRADICTS|out->2,1-HAS_VERDICT|out->3,2-WEAKENS|in->1,3-HAS_VERDICT|in->4,4-SUPPORTS|out->0;c=0-SUPERSEDED_BY|in->0:1,0-WEAKENS|in->1:1,0-WEAKENS|in->4:1,1-CONTRADICTS|out->2:1,1-HAS_VERDICT|out->3:1,2-WEAKENS|in->1:1,3-HAS_VERDICT|in->4:1,4-SUPPORTS|out->0:1",
   "sig_b": "n=4;t=0>0>1>2>3;el=\u2014,SUPERSEDED_BY|in,WEAKENS|in,CONTRADICTS|out,CONTRADICTS|in;e=0-SUPERSEDED_BY|in->0,0-WEAKENS|in->1,1-CONTRADICTS|out->2,2-CONTRADICTS|in->3;c=0-SUPERSEDED_BY|in->0:1,0-WEAKENS|in->1:1,1-CONTRADICTS|out->2:1,2-CONTRADICTS|in->3:1"
  }
 ]
}